Tests/__init__.py
Tests/test_aplicacion_ventas.py
Ventas/__init__.py
Ventas/descuentos.py
Ventas/exception.py
Ventas/gestor_ventas.py
Ventas/impuestos.py
Ventas/precios.py
aplicacion_ventas_ezamora-1.0.0.dist-info/licenses/LICENCE
aplicacion_ventas_ezamora-1.0.0.dist-info/METADATA
aplicacion_ventas_ezamora-1.0.0.dist-info/WHEEL
aplicacion_ventas_ezamora-1.0.0.dist-info/top_level.txt
aplicacion_ventas_ezamora-1.0.0.dist-info/RECORD
