Metadata-Version: 2.4
Name: Aplicacion_Ventas_EZamora
Version: 1.0.0
Summary: Aplicacion de ventas con manejo de impuestos y descuentos
Home-page: https://github.com/ErZamo/gestor/Aplicacion_Ventas
Author: Erick Zamora
Author-email: ErZamo@gmail.com
Classifier: Programming Language :: Python :: 3
Classifier: License :: OSI Approved :: MIT License
Classifier: Operating System :: OS Independent
Requires-Python: >=3.7
License-File: LICENCE
Dynamic: author
Dynamic: author-email
Dynamic: classifier
Dynamic: description
Dynamic: description-content-type
Dynamic: home-page
Dynamic: license-file
Dynamic: requires-python
Dynamic: summary
